crosscat/__init__.py
crosscat/CrossCatClient.py
crosscat/EngineTemplate.py
crosscat/HadoopEngine.py
crosscat/IPClusterEngine.py
crosscat/JSONRPCEngine.py
crosscat/LocalEngine.py
crosscat/MultiprocessingEngine.py
crosscat/version.py
crosscat/convergence_analysis/__init__.py
crosscat/convergence_analysis/automated_convergence_tests.py
crosscat/convergence_analysis/convergence_test.py
crosscat/convergence_analysis/generate_convergence_script.py
crosscat/convergence_analysis/parse_convergence_results.py
crosscat/convergence_analysis/plot_convergence_results.py
crosscat/cython_code/__init__.py
crosscat/cython_code/continuous_component_model_test.py
crosscat/cython_code/ContinuousComponentModel.so
crosscat/cython_code/CyclicComponentModel.so
crosscat/cython_code/mixed_state_test.py
crosscat/cython_code/MultinomialComponentModel.so
crosscat/cython_code/State.so
crosscat/cython_code/state_test.py
crosscat/cython_code/test_missing_value.py
crosscat/cython_code/test_multinomial_impute.py
crosscat/cython_code/test_pred_prob_and_density.py
crosscat/cython_code/test_sample.py
crosscat/jsonrpc_http/__init__.py
crosscat/jsonrpc_http/server_jsonrpc.py
crosscat/jsonrpc_http/stub_client_jsonrpc.py
crosscat/jsonrpc_http/test_engine.py
crosscat/jsonrpc_http/test_resume.py
crosscat/tests/__init__.py
crosscat/tests/cpp_long_tests.py
crosscat/tests/cpp_unit_tests.py
crosscat/tests/enumerate_utils.py
crosscat/tests/geweke_on_schemas.py
crosscat/tests/geweke_utils.py
crosscat/tests/mutual_information_test_utils.py
crosscat/tests/plot_utils.py
crosscat/tests/quality_test_utils.py
crosscat/tests/synthetic_data_generator.py
crosscat/tests/test_col_ensure.py
crosscat/tests/test_log_likelihood.py
crosscat/tests/test_pred_prob_and_density.py
crosscat/tests/test_sampler_enumeration.py
crosscat/tests/timing_analysis.py
crosscat/tests/timing_test_utils.py
crosscat/tests/component_model_extensions/__init__.py
crosscat-0.1.55.dist-info/DESCRIPTION.rst
crosscat-0.1.55.dist-info/METADATA
crosscat-0.1.55.dist-info/metadata.json
crosscat-0.1.55.dist-info/RECORD
crosscat-0.1.55.dist-info/top_level.txt
crosscat-0.1.55.dist-info/WHEEL
