Metadata-Version: 2.0
Name: crosscat
Version: 0.1.55
Summary: A domain-general, Bayesian method for analyzing high-dimensional data tables
Home-page: https://github.com/probcomp/crosscat
Author: MIT Probabilistic Computing Project
Author-email: bayesdb@mit.edu
License: Apache License, Version 2.0
Platform: UNKNOWN
Requires-Dist: cython (>=0.20.1)
Requires-Dist: numpy (>=1.7.0)
Requires-Dist: six
